{"id": "b57a9946-e27a-4582-9206-5ed5d64868c9", "display_name": "seesr", "description": null, "short_desc": null, "endpoints": [{"id": "root__get", "display_name": "root__get", "description": null, "short_desc": "Root", "path": "/", "parameters": [], "responses": {"200": {"content": {"application/json": {"schema": {"title": "Response Root  Get"}}}, "description": "Successful Response"}}, "timeout_s": null}, {"id": "start_shutdown_shutdown_post", "display_name": "start_shutdown_shutdown_post", "description": null, "short_desc": "Start Shutdown", "path": "/shutdown", "parameters": [], "responses": {"200": {"content": {"application/json": {"schema": {"title": "Response Start Shutdown Shutdown Post"}}}, "description": "Successful Response"}}, "timeout_s": null}, {"id": "predict_predictions_post", "display_name": "predict_predictions_post", "description": "Run a single prediction on the model", "short_desc": "Predict", "path": "/predictions", "parameters": [{"name": "prefer", "type": "string", "required": false, "default": null, "location": "header", "param_schema": {"type": "string", "title": "Prefer"}, "description": null}, {"name": "seed", "type": "integer", "required": false, "default": 231, "location": "body", "param_schema": {"type": "integer", "title": "Seed", "default": 231, "maximum": 2147483647, "minimum": 0, "x-order": 10, "description": "Seed"}, "description": "Seed"}, {"name": "image", "type": ["file", "string"], "required": true, "default": null, "location": "body", "param_schema": {"type": "string", "title": "Image", "format": "uri", "x-order": 0, "description": "Input image"}, "description": "Input image"}, {"name": "cfg_scale", "type": "number", "required": false, "default": 5.5, "location": "body", "param_schema": {"type": "number", "title": "Cfg Scale", "default": 5.5, "maximum": 10, "minimum": 0.1, "x-order": 4, "description": "Guidance scale, set value to >1 to use"}, "description": "Guidance scale, set value to >1 to use"}, {"name": "user_prompt", "type": "string", "required": false, "default": "", "location": "body", "param_schema": {"type": "string", "title": "User Prompt", "default": "", "x-order": 1, "description": "Prompt to condition on"}, "description": "Prompt to condition on"}, {"name": "sample_times", "type": "integer", "required": false, "default": 1, "location": "body", "param_schema": {"type": "integer", "title": "Sample Times", "default": 1, "maximum": 10, "minimum": 1, "x-order": 6, "description": "Number of samples to generate"}, "description": "Number of samples to generate"}, {"name": "scale_factor", "type": "integer", "required": false, "default": 4, "location": "body", "param_schema": {"type": "integer", "title": "Scale Factor", "default": 4, "x-order": 9, "description": "Scale factor"}, "description": "Scale factor"}, {"name": "negative_prompt", "type": "string", "required": false, "default": "dotted, noise, blur, lowres, smooth", "location": "body", "param_schema": {"type": "string", "title": "Negative Prompt", "default": "dotted, noise, blur, lowres, smooth", "x-order": 3, "description": "Prompt to remove"}, "description": "Prompt to remove"}, {"name": "positive_prompt", "type": "string", "required": false, "default": "clean, high-resolution, 8k", "location": "body", "param_schema": {"type": "string", "title": "Positive Prompt", "default": "clean, high-resolution, 8k", "x-order": 2, "description": "Prompt to add"}, "description": "Prompt to add"}, {"name": "latent_tiled_size", "type": "integer", "required": false, "default": 320, "location": "body", "param_schema": {"type": "integer", "title": "Latent Tiled Size", "default": 320, "maximum": 480, "minimum": 128, "x-order": 7, "description": "Size of latent tiles"}, "description": "Size of latent tiles"}, {"name": "num_inference_steps", "type": "integer", "required": false, "default": 50, "location": "body", "param_schema": {"type": "integer", "title": "Num Inference Steps", "default": 50, "maximum": 100, "minimum": 10, "x-order": 5, "description": "Number of inference steps"}, "description": "Number of inference steps"}, {"name": "latent_tiled_overlap", "type": "integer", "required": false, "default": 4, "location": "body", "param_schema": {"type": "integer", "title": "Latent Tiled Overlap", "default": 4, "maximum": 16, "minimum": 4, "x-order": 8, "description": "Overlap of latent tiles"}, "description": "Overlap of latent tiles"}], "responses": {"200": {"content": {"application/json": {"schema": {"$ref": "#/components/schemas/PredictionResponse"}}}, "description": "Successful Response"}, "422": {"content": {"application/json": {"schema": {"$ref": "#/components/schemas/HTTPValidationError"}}}, "description": "Validation Error"}}, "timeout_s": null}, {"id": "healthcheck_health_check_get", "display_name": "healthcheck_health_check_get", "description": null, "short_desc": "Healthcheck", "path": "/health-check", "parameters": [], "responses": {"200": {"content": {"application/json": {"schema": {"title": "Response Healthcheck Health Check Get"}}}, "description": "Successful Response"}}, "timeout_s": null}, {"id": "predict_idempotent_predictions__prediction_id__put", "display_name": "predict_idempotent_predictions__prediction_id__put", "description": "Run a single prediction on the model (idempotent creation).", "short_desc": "Predict Idempotent", "path": "/predictions/{prediction_id}", "parameters": [{"name": "prediction_id", "type": "string", "required": true, "default": null, "location": "path", "param_schema": {"type": "string", "title": "Prediction ID"}, "description": null}, {"name": "prefer", "type": "string", "required": false, "default": null, "location": "header", "param_schema": {"type": "string", "title": "Prefer"}, "description": null}, {"name": "Prediction Request", "type": "object", "required": true, "default": null, "location": "body", "param_schema": {"allOf": [{"$ref": "#/components/schemas/PredictionRequest"}], "title": "Prediction Request"}, "description": null}], "responses": {"200": {"content": {"application/json": {"schema": {"$ref": "#/components/schemas/PredictionResponse"}}}, "description": "Successful Response"}, "422": {"content": {"application/json": {"schema": {"$ref": "#/components/schemas/HTTPValidationError"}}}, "description": "Validation Error"}}, "timeout_s": null}, {"id": "cancel_predictions__prediction_id__cancel_post", "display_name": "cancel_predictions__prediction_id__cancel_post", "description": "Cancel a running prediction", "short_desc": "Cancel", "path": "/predictions/{prediction_id}/cancel", "parameters": [{"name": "prediction_id", "type": "string", "required": true, "default": null, "location": "path", "param_schema": {"type": "string", "title": "Prediction ID"}, "description": null}], "responses": {"200": {"content": {"application/json": {"schema": {"title": "Response Cancel Predictions  Prediction Id  Cancel Post"}}}, "description": "Successful Response"}, "422": {"content": {"application/json": {"schema": {"$ref": "#/components/schemas/HTTPValidationError"}}}, "description": "Validation Error"}}, "timeout_s": null}], "specification": "cog", "used_models": [], "category": ["0e50e16b-a3e3-443f-8bcd-d48b25d57ff6"], "family_id": "19ae03bc-9812-4c81-b566-1bd06026e00e", "service_address": {"url": "http://localhost:8001/v1/seesr"}, "created_at": "2025-06-11T09:05:17.215323+00:00", "version": "32f31963ad67665819f24eb23b20e74463e57f56"}